mbr/__init__.py
mbr/modeling.py
mbr/generation/__init__.py
mbr/generation/configuration_utils.py
mbr/generation/utils.py
mbr/metrics/__init__.py
mbr/metrics/base.py
mbr/metrics/comet.py
mbr-0.2.0.dist-info/METADATA
mbr-0.2.0.dist-info/WHEEL
mbr-0.2.0.dist-info/licenses/LICENSE
mbr-0.2.0.dist-info/RECORD
