Metadata-Version: 2.1
Name: mbr
Version: 0.2.0
Summary: Minimum Bayes risk decoding for Hugging Face Transformers
Project-URL: Homepage, https://github.com/ZurichNLP/mbr
Project-URL: Bug Tracker, https://github.com/ZurichNLP/mbr/issues
Author-email: Jannis Vamvas <vamvas@cl.uzh.ch>
License-File: LICENSE
Classifier: License :: OSI Approved :: MIT License
Classifier: Operating System :: OS Independent
Classifier: Programming Language :: Python :: 3
Requires-Python: >=3.9
Requires-Dist: cachetools
Requires-Dist: evaluate
Requires-Dist: sacrebleu
Requires-Dist: tqdm
Requires-Dist: transformers
